custom/__init__.py
custom/gigachat/__init__.py
custom/gigachat/configuration_deepseek.py
custom/gigachat/modelling_deepseek.py
custom/llama/__init__.py
custom/llama/modeling_llama.py
custom/llama/module.py
impruver/__init__.py
impruver/_recipe_registry.py
impruver/_cli/__init__.py
impruver/_cli/_parser.py
impruver/_cli/copy.py
impruver/_cli/download.py
impruver/_cli/list.py
impruver/_cli/run.py
impruver/_cli/subcommand.py
impruver/conversation/__init__.py
impruver/conversation/chat_history.py
impruver/conversation/generate.py
impruver/conversation/get_prompt.py
impruver/converters/__init__.py
impruver/converters/char_dialog_to_messages.py
impruver/converters/conversations_to_messages.py
impruver/converters/dialog_to_messages.py
impruver/converters/instruction_to_messages.py
impruver/converters/reasoning_to_messages.py
impruver/data/__init__.py
impruver/data/apply_chat_template.py
impruver/data/message.py
impruver/data/strategies.py
impruver/data/tokenizer.py
impruver/data/validate_messages.py
impruver/dataset/__init__.py
impruver/dataset/chat_dataset.py
impruver/dataset/raw_dataset.py
impruver/utils/__init__.py
impruver/utils/dynamic_import.py
impruver/utils/get_device.py
impruver/utils/get_dtype.py
impruver/utils/get_logger.py
impruver/utils/io.py
impruver/utils/set_seed.py
recipes/chat_transformers.py
recipes/compose_dataset.py
recipes/convert_gguf.py
recipes/finetune_transformers.py
recipes/finetune_unsloth.py
recipes/configs/GigaChat/20B-A3B_lora_o1.yaml
recipes/configs/T-lite-it/7B_lora_thinking.yaml
recipes/configs/YandexGPT/8B_lora_r1.yaml
recipes/configs/nanoGPT/30M_full_alpaca.yaml
recipes/configs/ruGPT-3.5/13B_lora_cot.yaml
recipes/configs/ruGPT-3.5/13B_lora_fc.yaml
recipes/configs/ruGPT-3.5/13B_lora_fcot.yaml
recipes/configs/ruGPT-3.5/13B_lora_saiga2.yaml
recipes/configs/rugpt3large/760M_full_fc.yaml
recipes/configs/rugpt3large/760M_full_saiga2.yaml
recipes/configs/rugpt3large/760M_lora_fc.yaml
recipes/configs/rugpt3large/760M_lora_saiga2.yaml
impruver-1.0.8.dist-info/LICENSE
impruver-1.0.8.dist-info/METADATA
impruver-1.0.8.dist-info/WHEEL
impruver-1.0.8.dist-info/entry_points.txt
impruver-1.0.8.dist-info/top_level.txt
impruver-1.0.8.dist-info/RECORD
