Metadata-Version: 2.2
Name: impruver
Version: 1.0.8
Summary: Transformer based LLM trainer
Author-email: Pavel Rykov <paul@drteam.rocks>
License: MIT License
Project-URL: GitHub, https://github.com/EvilFreelancer/impruver
Project-URL: Documentation, https://github.com/EvilFreelancer/impruver/wiki
Project-URL: Issues, https://github.com/EvilFreelancer/impruver/issues
Keywords: pytorch,transformers,finetuning,llm
Classifier: Programming Language :: Python :: 3
Classifier: License :: OSI Approved :: MIT License
Classifier: Operating System :: OS Independent
Requires-Python: >=3.12
License-File: LICENSE
Requires-Dist: pydantic>=2.10.4
Requires-Dist: pyyaml>=6.0.2
Requires-Dist: jsonlines>=4.0.0
Requires-Dist: fire>=0.7.0
Requires-Dist: datasketch>=1.6.5
Requires-Dist: torch>=2.5.1
Requires-Dist: datasets>=3.2.0
Requires-Dist: transformers>=4.47.1
Requires-Dist: huggingface-hub>=0.27.0
Requires-Dist: safetensors>=0.4.5
Requires-Dist: zstandard>=0.23.0
Requires-Dist: tokenizers>=0.21.0
Requires-Dist: tqdm>=4.67.1
Requires-Dist: bitsandbytes>=0.45.0
Requires-Dist: peft>=0.14.0
Requires-Dist: accelerate>=1.2.1
Provides-Extra: dev
Requires-Dist: wandb>=0.19.1; extra == "dev"
Requires-Dist: tiktoken>=0.8.0; extra == "dev"
Requires-Dist: torchao>=0.4.0; extra == "dev"
Requires-Dist: sentencepiece>=0.2.0; extra == "dev"
